facebook_collector/__init__.py
facebook_collector/brand.py
facebook_collector/constant.py
facebook_collector/graphql_handler.py
facebook_collector/hashtag.py
facebook_collector/keywords.py
facebook_collector/post_comment.py
facebook_collector/profile_by_graphAPI.py
facebook_collector/profile_by_selenium.py
facebook_collector/utils.py
facebook_collector-0.2.8.dist-info/licenses/LICENSE
tests/__init__.py
tests/test_hashtag.py
tests/test_keyword_collector.py
facebook_collector-0.2.8.dist-info/METADATA
facebook_collector-0.2.8.dist-info/WHEEL
facebook_collector-0.2.8.dist-info/top_level.txt
facebook_collector-0.2.8.dist-info/RECORD
