Metadata-Version: 2.4
Name: facebook_collector
Version: 0.2.8
Summary: A Python library for collecting data from Facebook using Selenium and GraphQL
Author: Vu Dinh
Author-email: vu.dinh@hiip.asia
License: MIT
Classifier: Development Status :: 3 - Alpha
Classifier: Intended Audience :: Developers
Classifier: Programming Language :: Python :: 3
Classifier: Programming Language :: Python :: 3.7
Classifier: Programming Language :: Python :: 3.8
Classifier: Programming Language :: Python :: 3.9
Requires-Python: >=3.7
License-File: LICENSE
Requires-Dist: selenium
Requires-Dist: requests
Requires-Dist: webdriver-manager>=3.8.0
Requires-Dist: python-dotenv>=0.19.0
Requires-Dist: pandas>=1.3.0
Requires-Dist: numpy>=1.21.0
Requires-Dist: pytz>=2021.1
Requires-Dist: sqlalchemy>=1.4.0
Requires-Dist: openpyxl>=3.0.0
Dynamic: author
Dynamic: author-email
Dynamic: classifier
Dynamic: license
Dynamic: license-file
Dynamic: requires-dist
Dynamic: requires-python
Dynamic: summary
